README.txt
setup.py
betahaus/__init__.py
betahaus.livesearch.egg-info/PKG-INFO
betahaus.livesearch.egg-info/SOURCES.txt
betahaus.livesearch.egg-info/dependency_links.txt
betahaus.livesearch.egg-info/entry_points.txt
betahaus.livesearch.egg-info/namespace_packages.txt
betahaus.livesearch.egg-info/not-zip-safe
betahaus.livesearch.egg-info/requires.txt
betahaus.livesearch.egg-info/top_level.txt
betahaus/livesearch/__init__.py
betahaus/livesearch/configure.zcml
betahaus/livesearch/browser/__init__.py
betahaus/livesearch/browser/configure.zcml
betahaus/livesearch/browser/livesearch_reply.pt
betahaus/livesearch/browser/livesearch_reply.py
betahaus/livesearch/profiles/default/jsregistry.xml
betahaus/livesearch/profiles/default/skins.xml
betahaus/livesearch/skins/betahaus_livesearch/livesearch.js
betahaus/livesearch/tests/__init__.py
betahaus/livesearch/tests/base.py
betahaus/livesearch/tests/test_livesearch.py
docs/HISTORY.txt
docs/INSTALL.txt
docs/LICENSE.GPL
docs/LICENSE.txt