Metadata-Version: 1.0
Name: betahaus.livesearch
Version: 0.1b2
Summary: Replaces regular livesearch with a sane template
Home-page: http://pypi.python.org/pypi/betahaus.livesearch
Author: Robin Harms Oredsson
Author-email: robin@betahaus.net
License: GPL
Keywords: plone
Platform: UNKNOWN
Classifier: Framework :: Plone
Classifier: Programming Language :: Python
Classifier: Development Status :: 4 - Beta
